libre_translate_api/__init__.py
libre_translate_api/answer.py
libre_translate_api/api.py
free_libretranslate_api-0.0.2.dist-info/METADATA
free_libretranslate_api-0.0.2.dist-info/WHEEL
free_libretranslate_api-0.0.2.dist-info/top_level.txt
free_libretranslate_api-0.0.2.dist-info/RECORD
