Metadata-Version: 2.1
Name: free-libretranslate-api
Version: 0.0.2
Summary: Бесплатный API LibreTranslate
Author: Ktoto
Project-URL: GitHub, https://github.com/KtotoNekt/FreeLibreTranslateAPI
Project-URL: CodeBerg, https://codeberg.org/Ktoto/FreeLibreTranslateAPI
Classifier: Programming Language :: Python :: 3
Classifier: License :: OSI Approved :: MIT License
Classifier: Operating System :: OS Independent
Requires-Python: >=3.8
Requires-Dist: requests
Requires-Dist: requests-toolbelt
